burstlogging.py
setup.py
burstlogging.egg-info/PKG-INFO
burstlogging.egg-info/SOURCES.txt
burstlogging.egg-info/dependency_links.txt
burstlogging.egg-info/top_level.txt