Metadata-Version: 1.1
Name: burstlogging
Version: 0.2
Summary: Burst logging library.
Home-page: https://github.com/loomchild/burstlogging
Author: Jarek Lipski
Author-email: pub@loomchild.net
License: MIT
Keywords: logging
Platform: UNKNOWN
Classifier: Development Status :: 3 - Alpha
Classifier: Topic :: Utilities
Classifier: License :: OSI Approved :: MIT License
